MANIFEST.in
README.md
setup.py
hedfpy.egg-info/PKG-INFO
hedfpy.egg-info/SOURCES.txt
hedfpy.egg-info/dependency_links.txt
hedfpy.egg-info/not-zip-safe
hedfpy.egg-info/top_level.txt
src/CommandLineOperator.py
src/EDFOperator.py
src/EyeSignalOperator.py
src/HDFEyeOperator.py
src/Operator.py
src/__init__.py
src/log.py
test/introduction.ipynb
test/tk_1_2014-10-06_16.44.11.edf
test/.ipynb_checkpoints/introduction-checkpoint.ipynb