Metadata-Version: 1.1
Name: hedfpy
Version: 0.0.dev3
Summary: convert SR Research eyelink edf output to tabular hdf5 format.
Home-page: http://tknapen.github.io/hedfpy
Author: Tomas Knapen
Author-email: tknapen@gmail.com
License: The MIT License (MIT)
Download-URL: https://github.com/tknapen/hedfpy
Platform: any
Classifier: Intended Audience :: Science/Research
Classifier: Intended Audience :: Developers
Classifier: License :: OSI Approved
Classifier: Programming Language :: Python
Classifier: Topic :: Software Development
Classifier: Topic :: Scientific/Engineering
Classifier: Operating System :: POSIX
Classifier: Operating System :: Unix
Classifier: Operating System :: MacOS
